{
	"format_version": "1.8.0",
	"animations": {
		"marche": {
			"animation_length": 1.75,
			"bones": {
				"Piedgauche": {
					"position": {
						"0.0": {
							"vector": [0, 0, -1]
						},
						"0.25": {
							"vector": [0, 0, -2]
						},
						"0.5": {
							"vector": [0, 0, -1]
						},
						"0.75": {
							"vector": [0, 0, 0]
						},
						"1.0": {
							"vector": [0, 0, 1]
						},
						"1.25": {
							"vector": [0, 0, 2]
						},
						"1.5": {
							"vector": [0, 0, 1]
						},
						"1.75": {
							"vector": [0, 0, 0]
						}
					}
				},
				"PiedDroit": {
					"position": {
						"0.0": {
							"vector": [0, 0, 1]
						},
						"0.25": {
							"vector": [0, 0, 2]
						},
						"0.5": {
							"vector": [0, 0, 1]
						},
						"0.75": {
							"vector": [0, 0, 0]
						},
						"1.0": {
							"vector": [0, 0, -1]
						},
						"1.25": {
							"vector": [0, 0, -2]
						},
						"1.5": {
							"vector": [0, 0, -1]
						},
						"1.75": {
							"vector": [0, 0, 0]
						}
					}
				}
			}
		},
		"Attack": {
			"animation_length": 0.75,
			"bones": {
				"Brasgauche": {
					"rotation": {
						"0.0": {
							"vector": [-60, 0, 0]
						},
						"0.75": {
							"vector": [-115, 0, 0]
						}
					},
					"position": {
						"0.0": {
							"vector": [0, 9, -18]
						},
						"0.75": {
							"vector": [0, 30, -22]
						}
					}
				},
				"Brasdroit": {
					"rotation": {
						"0.0": {
							"vector": [-60, 0, 0]
						},
						"0.75": {
							"vector": [-115, 0, 0]
						}
					},
					"position": {
						"0.0": {
							"vector": [0, 9, -18]
						},
						"0.75": {
							"vector": [0, 30, -22]
						}
					}
				}
			}
		}
	},
	"geckolib_format_version": 2
}